onedrive_sharepoint/__init__.py
onedrive_sharepoint/main.py
onedrive_sharepoint-0.1.14.dist-info/LICENSE
onedrive_sharepoint-0.1.14.dist-info/METADATA
onedrive_sharepoint-0.1.14.dist-info/WHEEL
onedrive_sharepoint-0.1.14.dist-info/top_level.txt
onedrive_sharepoint-0.1.14.dist-info/RECORD
